pocket/__init__.py
pocket/context.py
pocket/general_context.py
pocket/general_settings.py
pocket/mediator.py
pocket/runtime.py
pocket/settings.py
pocket/utils.py
pocket/cli/__init__.py
pocket/cli/awscontainer_cli.py
pocket/cli/deploy_cli.py
pocket/cli/main_cli.py
pocket/cli/neon_cli.py
pocket/cli/s3_cli.py
pocket/cli/spa_cli.py
pocket/cli/status_cli.py
pocket/cli/vpc_cli.py
pocket/django/__init__.py
pocket/django/context.py
pocket/django/django_cli.py
pocket/django/lambda_handlers.py
pocket/django/runtime.py
pocket/django/settings.py
pocket/django/urls.py
pocket/django/utils.py
pocket/resources/__init__.py
pocket/resources/awscontainer.py
pocket/resources/base.py
pocket/resources/neon.py
pocket/resources/s3.py
pocket/resources/spa.py
pocket/resources/vpc.py
pocket/resources/aws/__init__.py
pocket/resources/aws/cloudformation.py
pocket/resources/aws/ecr.py
pocket/resources/aws/efs.py
pocket/resources/aws/lambdahandler.py
pocket/resources/aws/secretsmanager.py
pocket/templates/cloudformation/awscontainer.yaml
pocket/templates/cloudformation/spa.yaml
pocket/templates/cloudformation/vpc.yaml
pocket/templates/init/django-dotenv.env
pocket/templates/init/django-settings.py
pocket/templates/init/pocket.Dockerfile
pocket/templates/init/pocket_simple.toml
magic_pocket-0.1.1.dist-info/entry_points.txt
magic_pocket-0.1.1.dist-info/LICENSE
magic_pocket-0.1.1.dist-info/WHEEL
magic_pocket-0.1.1.dist-info/METADATA
magic_pocket-0.1.1.dist-info/RECORD
