Metadata-Version: 2.1
Name: magic-pocket
Version: 0.1.1
Summary: Deploy system for Django projects.
Author-email: Masaaki Yasui <yasu@worgue.com>
Classifier: License :: OSI Approved :: MIT License
Requires-Dist: click>=8.1.7
Requires-Dist: tomli>=1.1.0 ; python_version < '3.11'
Requires-Dist: mergedeep>=1.3.4
Requires-Dist: pydantic>=2.5.3
Requires-Dist: pydantic-settings>=2.1.0
Requires-Dist: boto3>=1.34.28
Requires-Dist: rich>=13.7.0
Requires-Dist: deepdiff>=6.7.1
Requires-Dist: pyyaml>=6.0.1
Requires-Dist: python-on-whales>=0.68.0
Requires-Dist: jinja2>=3.1.3
Requires-Dist: awslambdaric>=2.0.10
Requires-Dist: apig_wsgi>=2.18.0
Requires-Dist: django-storages>=1.14.2,!=1.14.3
Requires-Dist: django>=4.2.0 ; extra == "django"
Project-URL: Documentation, https://worgue.github.io/magic-pocket/
Project-URL: Source, https://github.com/worgue/magic-pocket
Provides-Extra: django
